python_packaging_am/__init__.py
python_packaging_am/maths.py
python_packaging_am-0.0.3.dist-info/LICENSE
python_packaging_am-0.0.3.dist-info/METADATA
python_packaging_am-0.0.3.dist-info/WHEEL
python_packaging_am-0.0.3.dist-info/top_level.txt
python_packaging_am-0.0.3.dist-info/RECORD
