Metadata-Version: 2.1
Name: python-packaging-am
Version: 0.0.3
Summary: Example of how to package Python code for release
Home-page: https://github.com/gitamartin01/python-packaging-am
Author: Alexia Martin
Author-email: amartin01@icr.ac.uk
License: MIT
Platform: UNKNOWN
Requires-Python: >=3.7
License-File: LICENSE
Requires-Dist: numpy (>=1.22.2)
Requires-Dist: pandas
Provides-Extra: dev
Requires-Dist: bump2version ; extra == 'dev'
